atlaslib/__init__.py
atlaslib/loader.py
atlaslib-1.1.dist-info/LICENSE
atlaslib-1.1.dist-info/METADATA
atlaslib-1.1.dist-info/WHEEL
atlaslib-1.1.dist-info/top_level.txt
atlaslib-1.1.dist-info/RECORD
